LICENSE
README.md
setup.py
pypi_scraper/__init__.py
rednet_scraper.egg-info/PKG-INFO
rednet_scraper.egg-info/SOURCES.txt
rednet_scraper.egg-info/dependency_links.txt
rednet_scraper.egg-info/requires.txt
rednet_scraper.egg-info/top_level.txt